bird_or_bicycle/__init__.py
bird_or_bicycle/dataset.py
bird_or_bicycle/iterator.py
bird_or_bicycle-0.0.3.data/scripts/bird-or-bicycle-download
bird_or_bicycle-0.0.3.data/scripts/bird-or-bicycle-verify
bird_or_bicycle-0.0.3.dist-info/METADATA
bird_or_bicycle-0.0.3.dist-info/RECORD
bird_or_bicycle-0.0.3.dist-info/WHEEL
bird_or_bicycle-0.0.3.dist-info/top_level.txt
